nmine/__init__.py
nmine/ianatlds.py
nmine/main.py
nmine/output.py
nmine/streamfind.py
nmine/strfind.py
nmine-3.2.2.dist-info/LICENSE
nmine-3.2.2.dist-info/METADATA
nmine-3.2.2.dist-info/WHEEL
nmine-3.2.2.dist-info/entry_points.txt
nmine-3.2.2.dist-info/top_level.txt
nmine-3.2.2.dist-info/RECORD
