Metadata-Version: 2.2
Name: nmine
Version: 3.2.2
Summary: Combines nmap output and DNS data to produce HTTP[S] URLs of interest.
Author-email: Steve Benson <steve@xelphene.net>
Project-URL: Homepage, https://github.com/xelphene/nmine
Project-URL: Bug Tracker, https://github.com/xelphene/nmine/issues
Classifier: Programming Language :: Python :: 3
Classifier: License :: OSI Approved :: GNU General Public License v3 (GPLv3)
Classifier: Operating System :: OS Independent
Requires-Python: >=3.7
License-File: LICENSE
Requires-Dist: ipcidrtree>=1.3.0
